easyo2p/__init__.py
easyo2p/_constants.py
easyo2p/_data.py
easyo2p/_foreign_keys.py
easyo2p/_indexes.py
easyo2p/_main.py
easyo2p/_sequences.py
easyo2p/_tables.py
easyo2p/_triggers.py
easyo2p-1.0.0.dist-info/LICENSE
easyo2p-1.0.0.dist-info/METADATA
easyo2p-1.0.0.dist-info/WHEEL
easyo2p-1.0.0.dist-info/top_level.txt
easyo2p-1.0.0.dist-info/RECORD
