Metadata-Version: 2.1
Name: easyo2p
Version: 1.0.0
Summary: Oracle to PostgreSQL migration for Python
Home-page: https://github.com/rikfair/easyo2p
Author: rikfair
Author-email: mail4rik-pypi@yahoo.com
License: MIT
Project-URL: Bug Tracker, https://github.com/rikfair/easyo2p/issues
Project-URL: Documentation, https://easyo2p.readthedocs.io/
Classifier: Development Status :: 5 - Production/Stable
Classifier: Intended Audience :: Developers
Classifier: License :: OSI Approved :: MIT License
Classifier: Operating System :: OS Independent
Classifier: Programming Language :: Python :: 3
Classifier: Programming Language :: Python :: 3 :: Only
Classifier: Topic :: Database
Classifier: Topic :: Utilities
Requires-Python: >=3.10
License-File: LICENSE
